d3m/core/__init__.py
d3m/core/abstractions.py
d3m/core/helpers.py
d3m/core/message.py
d3m/core/py.typed
d3m/core/types.py
dddmisc_core-0.7.1.dist-info/LICENSE
dddmisc_core-0.7.1.dist-info/METADATA
dddmisc_core-0.7.1.dist-info/WHEEL
dddmisc_core-0.7.1.dist-info/RECORD
