Metadata-Version: 2.1
Name: dddmisc-core
Version: 0.7.1
Summary: This package provides the core interfaces and types for dddmisc packages family
Home-page: https://dddmisc.github.io/dddmisc-docs/
License: MIT
Author: Vladislav Vorobyov
Author-email: vladislav.vorobyov@gmail.com
Requires-Python: >=3.10,<4.0
Classifier: License :: OSI Approved :: MIT License
Classifier: Programming Language :: Python :: 3
Classifier: Programming Language :: Python :: 3.10
Classifier: Programming Language :: Python :: 3.11
Classifier: Programming Language :: Python :: 3.12
Requires-Dist: pydantic (>=2.1.0,<3.0.0)
Project-URL: Repository, https://github.com/dddmisc/dddmisc
